Pokemon_Library/__init__.py
Pokemon_Library/pokemon.csv
Pokemon_Library/random_pokemon.py
Pokemon_Library-1.0.0.dist-info/METADATA
Pokemon_Library-1.0.0.dist-info/WHEEL
Pokemon_Library-1.0.0.dist-info/top_level.txt
Pokemon_Library-1.0.0.dist-info/RECORD
